LICENSE
README.md
pyproject.toml
setup.cfg
setup.py
elasticsearch_reindex/__init__.py
elasticsearch_reindex/__main__.py
elasticsearch_reindex/cli.py
elasticsearch_reindex/client.py
elasticsearch_reindex/const.py
elasticsearch_reindex/errors.py
elasticsearch_reindex/logger.py
elasticsearch_reindex/manager.py
elasticsearch_reindex/py.typed
elasticsearch_reindex/reindex.py
elasticsearch_reindex/schema.py
elasticsearch_reindex/utils.py
elasticsearch_reindex.egg-info/PKG-INFO
elasticsearch_reindex.egg-info/SOURCES.txt
elasticsearch_reindex.egg-info/dependency_links.txt
elasticsearch_reindex.egg-info/entry_points.txt
elasticsearch_reindex.egg-info/requires.txt
elasticsearch_reindex.egg-info/top_level.txt