Metadata-Version: 2.1
Name: elasticsearch-reindex
Version: 1.3.0
Summary: Python package for simple migration elasticsearch indexes between different elasticsearch nodes.
Home-page: https://github.com/borys25ol/elasticsearch-reindex
Author: Borys Oliinyk
Author-email: oleynik.boris@gmail.com
License: MIT
Classifier: License :: OSI Approved :: MIT License
Classifier: Programming Language :: Python :: 3.10
Classifier: Programming Language :: Python :: 3.11
Classifier: Programming Language :: Python :: 3.12
Requires-Python: >=3.10
License-File: LICENSE
Requires-Dist: click>8
Requires-Dist: elasticsearch>7
Requires-Dist: requests>=2.32.3
